notebook/__init__.py
over_under_sampler/__init__.py
over_under_sampler/over_sampling/__init__.py
over_under_sampler/over_sampling/over_sampler.py
over_under_sampler/under_sampling/__init__.py
over_under_sampler/under_sampling/under_sampler.py
over_under_sampler/up_and_down_sampling/__init__.py
over_under_sampler/up_and_down_sampling/under_over_sampler.py
over_under_sampler/utilites/__init__.py
over_under_sampler/utilites/yaml_reader.py
resources/__init__.py
tests/__init__.py
tests/unit/__init__.py
tests/unit/prepare_test_data.py
tests/unit/over_sampling/__init__.py
tests/unit/over_sampling/over_sampler_test.py
tests/unit/under_sampling/__init__.py
tests/unit/under_sampling/under_sampler_test.py
tests/unit/up_and_down_sampling/__init__.py
tests/unit/up_and_down_sampling/under_over_sampler_test.py
tests/unit/utilites/__init__.py
tests/unit/utilites/yaml_reader_test.py
under_over_sampling_smote_utility-0.1.0.dist-info/METADATA
under_over_sampling_smote_utility-0.1.0.dist-info/WHEEL
under_over_sampling_smote_utility-0.1.0.dist-info/top_level.txt
under_over_sampling_smote_utility-0.1.0.dist-info/RECORD
